discord_paginator/__init__.py
discord_paginator/discord_paginator.py
discord_paginator-0.3.1.dist-info/METADATA
discord_paginator-0.3.1.dist-info/WHEEL
discord_paginator-0.3.1.dist-info/top_level.txt
discord_paginator-0.3.1.dist-info/RECORD
